seedmeopenmm/__init__.py
seedmeopenmm/seedmeopenmm.py
seedmeopenmm-0.1.1.dist-info/RECORD
seedmeopenmm-0.1.1.dist-info/top_level.txt
seedmeopenmm-0.1.1.dist-info/METADATA
seedmeopenmm-0.1.1.dist-info/WHEEL
seedmeopenmm-0.1.1.dist-info/DESCRIPTION.rst
seedmeopenmm-0.1.1.dist-info/metadata.json
