Metadata-Version: 2.0
Name: seedmeopenmm
Version: 0.1.1
Summary: seedmeopenmm contains a stated data reporter that connects post Openmm simulation results to SeedMe
Home-page: https://github.com/sqamara/seedmeopenmm
Author: Sebastian Amara
Author-email: sqamara@ucsd.edu
License: BSD
Keywords: seedmeopenmm
Platform: UNKNOWN
Classifier: Development Status :: 2 - Pre-Alpha
Classifier: Intended Audience :: Developers
Classifier: License :: OSI Approved :: BSD License
Classifier: Natural Language :: English
Classifier: Programming Language :: Python :: 2
Classifier: Programming Language :: Python :: 2.6
Classifier: Programming Language :: Python :: 2.7
Classifier: Programming Language :: Python :: 3
Classifier: Programming Language :: Python :: 3.3
Classifier: Programming Language :: Python :: 3.4
Requires-Dist: openmm
Requires-Dist: seedme
